{"updated_at":"2026-07-21T21:13:21.113701+00:00","appid":3678970,"currency":"USD","exchange_rates":{"BRL":5.098788,"EUR":0.875778,"GBP":0.744372},"prices":{"Empire 50th Anniversary Coin":{"sell":93,"sell_text":"$0.93","listings":6503},"Kingdom 50th Anniversary Coin":{"sell":21,"sell_text":"$0.21","listings":15635},"Twilight Amethyst":{"sell":12,"sell_text":"$0.12","listings":15094},"Scroll of Arcana Inscription":{"sell":26,"sell_text":"$0.26","listings":4559},"Shadow Bow (Beyond) A":{"sell":87,"sell_text":"$0.87","listings":779},"Scroll of Immortal Inscription":{"sell":7,"sell_text":"$0.07","listings":18757},"Empire 10th Anniversary Coin":{"sell":6,"sell_text":"$0.06","listings":26650},"Frozen Orb (Arcana) A":{"sell":269,"sell_text":"$2.69","listings":876},"Dimensional Arrow (Beyond) A":{"sell":213,"sell_text":"$2.13","listings":272},"Dimensional Armor (Beyond) A":{"sell":39,"sell_text":"$0.39","listings":1126}}}