{"updated_at":"2026-06-29T04:15:30.818876+00:00","appid":3678970,"currency":"USD","exchange_rates":{"BRL":5.173169,"EUR":0.878247,"GBP":0.757693},"prices":{"Kingdom 100th Anniversary Coin":{"sell":966,"sell_text":"$9.66","listings":21},"Frozen Orb (Arcana) A":{"sell":328,"sell_text":"$3.28","listings":238},"Empire 50th Anniversary Coin":{"sell":231,"sell_text":"$2.31","listings":2379},"Kingdom 50th Anniversary Coin":{"sell":82,"sell_text":"$0.82","listings":7172},"Knight Boots (Arcana) A":{"sell":259,"sell_text":"$2.59","listings":989},"Twilight Amethyst":{"sell":77,"sell_text":"$0.77","listings":4338},"Soulstone - Torment":{"sell":6,"sell_text":"$0.06","listings":62401},"Scroll of Immortal Inscription":{"sell":25,"sell_text":"$0.25","listings":4373},"Astral Diamond":{"sell":35,"sell_text":"$0.35","listings":1842},"Phantom Emerald":{"sell":43,"sell_text":"$0.43","listings":4454}}}