{"updated_at":"2026-07-11T19:08:49.402788+00:00","appid":3678970,"currency":"USD","exchange_rates":{"BRL":5.114592,"EUR":0.875572,"GBP":0.745953},"prices":{"Empire 50th Anniversary Coin":{"sell":70,"sell_text":"$0.70","listings":3284},"Kingdom 50th Anniversary Coin":{"sell":29,"sell_text":"$0.29","listings":9332},"Frozen Orb (Arcana) A":{"sell":244,"sell_text":"$2.44","listings":557},"Twilight Amethyst":{"sell":34,"sell_text":"$0.34","listings":7948},"Scroll of Arcana Inscription":{"sell":47,"sell_text":"$0.47","listings":2638},"Scroll of Immortal Inscription":{"sell":14,"sell_text":"$0.14","listings":7650},"Phantom Emerald":{"sell":17,"sell_text":"$0.17","listings":8121},"Shadow Bow (Beyond) A":{"sell":57,"sell_text":"$0.57","listings":756},"Knight Boots (Arcana) A":{"sell":26,"sell_text":"$0.26","listings":3366},"Astral Diamond":{"sell":15,"sell_text":"$0.15","listings":5559}}}